odoo10_addon_account_invoice_download_weboob-10.0.1.0.0.99.dev11-nspkg.pth
odoo/addons/account_invoice_download_weboob/README.rst
odoo/addons/account_invoice_download_weboob/__init__.py
odoo/addons/account_invoice_download_weboob/__manifest__.py
odoo/addons/account_invoice_download_weboob/post_install.py
odoo/addons/account_invoice_download_weboob/i18n/account_invoice_download_weboob.pot
odoo/addons/account_invoice_download_weboob/i18n/nl.po
odoo/addons/account_invoice_download_weboob/models/__init__.py
odoo/addons/account_invoice_download_weboob/models/account_invoice_download_config.py
odoo/addons/account_invoice_download_weboob/models/weboob_module.py
odoo/addons/account_invoice_download_weboob/models/weboob_parameter.py
odoo/addons/account_invoice_download_weboob/security/ir.model.access.csv
odoo/addons/account_invoice_download_weboob/static/description/icon.png
odoo/addons/account_invoice_download_weboob/views/account_invoice_download_config.xml
odoo/addons/account_invoice_download_weboob/views/weboob_module.xml
odoo/addons/account_invoice_download_weboob/wizard/__init__.py
odoo/addons/account_invoice_download_weboob/wizard/weboob_module_update.py
odoo/addons/account_invoice_download_weboob/wizard/weboob_module_update_view.xml
odoo10_addon_account_invoice_download_weboob-10.0.1.0.0.99.dev11.dist-info/METADATA
odoo10_addon_account_invoice_download_weboob-10.0.1.0.0.99.dev11.dist-info/WHEEL
odoo10_addon_account_invoice_download_weboob-10.0.1.0.0.99.dev11.dist-info/namespace_packages.txt
odoo10_addon_account_invoice_download_weboob-10.0.1.0.0.99.dev11.dist-info/top_level.txt
odoo10_addon_account_invoice_download_weboob-10.0.1.0.0.99.dev11.dist-info/RECORD
